{
  "no": 12,
  "name": "Shani Raja",
  "author": [10],
  "avatar": "1681918_d7a1_6.jpg",
  "average": 4.4,
  "reviews": 8891,
  "students": 124737,
  "courses": 7,
  "description": "%3Cdiv%20class%3D%22instructor__job-title%22%3E%0A%20%20%20%20%20%20%20%20Editor%2C%20Writing%20Coach%20%26amp%3B%20Lecturer%0A%20%20%20%20%3C/div%3E%3Cdiv%20class%3D%22instructor__description%22%20user-tracker-click%3D%22%22%20data-user-tracker-schema%3D%22action-logs%22%20data-user-tracker-object-id%3D%22736456%22%20data-user-tracker-action%3D%22full-instructor-biography-read%22%20data-user-tracker-target-selector-class%3D%22js-simple-collapse-more-btn%22%20data-user-tracker-user-id%3D%22None%22%3E%0A%20%20%20%20%20%20%20%20%20%20%20%20%20%20%3Cdiv%20class%3D%22instructor__expand-description%20js-simple-collapse%22%20data-more%3D%22+%20View%20More%22%20style%3D%22max-height%3A%20none%3B%22%3E%0A%20%20%20%20%20%20%20%20%20%20%20%20%20%20%20%20%20%20%3Cdiv%20class%3D%22js-simple-collapse-inner%22%3E%0A%20%20%20%20%20%20%20%20%20%20%20%20%20%20%20%20%20%20%20%20%20%20%3Cp%20style%3D%22%22%3E%20%20%09%20%20%20%20%20%20%20%20%20%20%20%20%20%20%20%20%20%20%20%20%20%20%20%20%20%20%20%20%20%20%20%20%20%20%20%20%20%20%20Shani%20Raja%20teaches%20top%20journalists%20how%20to%20improve%20their%20writing%20and%20has%20written%20and%20edited%20for%20some%20of%20the%20world%27s%20biggest%20news%20organizations%2C%20including%20The%20Wall%20Street%20Journal%2C%20The%20Economist%2C%20Financial%20Times%20and%20Bloomberg%20News.%20Shani%20has%20also%20taught%20advanced%20writing%20skills%20to%20professionals%20and%20edited%20for%20leading%20global%20companies%20from%20Microsoft%20and%20IBM%20to%20PwC.%20He%20also%20teaches%20journalism%20to%20undergraduates.%20%20%3C/p%3E%0A%20%20%20%20%20%20%20%20%20%20%20%20%20%20%20%20%20%20%3C/div%3E%0A%20%20%20%20%20%20%20%20%20%20%20%20%20%20%3C/div%3E%0A%20%20%20%20%20%20%20%20%20%20%3C/div%3E"
}
